{
	"type": "Feature",
	"properties": {
		"FIPS": "NT",
		"ISO2": "AN",
		"ISO3": "ANT",
		"UN": 530,
		"NAME": "Netherlands Antilles",
		"AREA": 80,
		"POP2005": 186392,
		"REGION": 19,
		"SUBREGION": 29,
		"LON": -68.87,
		"LAT": 12.123
	},
	"bbox": [
		-69.16,
		12.02,
		-62.94,
		17.52
	],
	"geometry": {
		"type": "MultiPolygon",
		"coordinates": [
			[
				[
					[
						-68.2,
						12.22
					],
					[
						-68.19,
						12.21
					],
					[
						-68.19,
						12.2
					],
					[
						-68.21,
						12.11
					],
					[
						-68.23,
						12.04
					],
					[
						-68.24,
						12.03
					],
					[
						-68.24,
						12.02
					],
					[
						-68.25,
						12.02
					],
					[
						-68.26,
						12.02
					],
					[
						-68.26,
						12.03
					],
					[
						-68.28,
						12.05
					],
					[
						-68.28,
						12.06
					],
					[
						-68.29,
						12.1
					],
					[
						-68.28,
						12.14
					],
					[
						-68.28,
						12.15
					],
					[
						-68.28,
						12.16
					],
					[
						-68.29,
						12.17
					],
					[
						-68.29,
						12.18
					],
					[
						-68.3,
						12.2
					],
					[
						-68.3,
						12.2
					],
					[
						-68.31,
						12.21
					],
					[
						-68.33,
						12.22
					],
					[
						-68.35,
						12.22
					],
					[
						-68.37,
						12.22
					],
					[
						-68.39,
						12.22
					],
					[
						-68.39,
						12.22
					],
					[
						-68.4,
						12.22
					],
					[
						-68.4,
						12.22
					],
					[
						-68.42,
						12.25
					],
					[
						-68.42,
						12.26
					],
					[
						-68.4,
						12.29
					],
					[
						-68.4,
						12.3
					],
					[
						-68.4,
						12.3
					],
					[
						-68.38,
						12.31
					],
					[
						-68.37,
						12.31
					],
					[
						-68.36,
						12.31
					],
					[
						-68.2,
						12.22
					],
					[
						-68.2,
						12.22
					]
				]
			],
			[
				[
					[
						-68.97,
						12.2
					],
					[
						-68.91,
						12.18
					],
					[
						-68.89,
						12.18
					],
					[
						-68.88,
						12.18
					],
					[
						-68.86,
						12.18
					],
					[
						-68.85,
						12.18
					],
					[
						-68.84,
						12.17
					],
					[
						-68.82,
						12.16
					],
					[
						-68.75,
						12.06
					],
					[
						-68.75,
						12.04
					],
					[
						-68.8,
						12.04
					],
					[
						-68.82,
						12.04
					],
					[
						-68.83,
						12.05
					],
					[
						-68.83,
						12.05
					],
					[
						-68.96,
						12.11
					],
					[
						-68.97,
						12.12
					],
					[
						-69.06,
						12.19
					],
					[
						-69.13,
						12.27
					],
					[
						-69.16,
						12.31
					],
					[
						-69.16,
						12.37
					],
					[
						-69.15,
						12.38
					],
					[
						-69.1,
						12.36
					],
					[
						-69.08,
						12.35
					],
					[
						-69.08,
						12.35
					],
					[
						-69.07,
						12.33
					],
					[
						-69.06,
						12.31
					],
					[
						-69.06,
						12.29
					],
					[
						-69.05,
						12.27
					],
					[
						-69.04,
						12.26
					],
					[
						-69.03,
						12.24
					],
					[
						-69.03,
						12.24
					],
					[
						-69,
						12.22
					],
					[
						-68.98,
						12.2
					],
					[
						-68.97,
						12.2
					]
				]
			],
			[
				[
					[
						-62.96,
						17.46
					],
					[
						-62.97,
						17.46
					],
					[
						-62.98,
						17.46
					],
					[
						-62.98,
						17.46
					],
					[
						-63,
						17.49
					],
					[
						-63,
						17.49
					],
					[
						-63,
						17.51
					],
					[
						-63,
						17.52
					],
					[
						-62.99,
						17.52
					],
					[
						-62.99,
						17.52
					],
					[
						-62.94,
						17.49
					],
					[
						-62.94,
						17.49
					],
					[
						-62.94,
						17.49
					],
					[
						-62.94,
						17.47
					],
					[
						-62.95,
						17.47
					],
					[
						-62.95,
						17.46
					],
					[
						-62.96,
						17.46
					]
				]
			]
		]
	}
}